[
  {
    "id" : "befb95bf-38ba-4185-b044-3f666a68cc5b",
    "prId" : 27571,
    "prUrl" : "https://github.com/apache/spark/pull/27571#pullrequestreview-359385328",
    "prSource" : "GitHub",
    "comments" : [
      {
        "id" : "44636476-0d33-45e5-b7c6-b01ed0a6ac9c",
        "parentId" : null,
        "authorId" : "99765afe-8dbe-4d5f-9ad3-d5bc40f0462b",
        "body" : "same as the classifier example, I guess add ```summary(model)```, ```head(predictions)``` and also add ```sparkR.session.stop()``` in the end?\r\n",
        "createdAt" : "2020-02-16T07:53:25Z",
        "updatedAt" : "2020-04-09T05:21:50Z",
        "lastEditedBy" : "99765afe-8dbe-4d5f-9ad3-d5bc40f0462b",
        "tags" : [
        ]
      }
    ],
    "commit" : "2d1f8b1e1546301dee709e7d4ae38dec5deafac0",
    "line" : 41,
    "diffHunk" : "@@ -1,1 +39,43 @@\n# Prediction\npredictions <- predict(model, test)\nhead(predictions)\n# $example off$"
  }
]