[
  {
    "id" : "2a8b5219-b434-4f5f-a2d2-aa9929be2e06",
    "prId" : 32401,
    "prUrl" : "https://github.com/apache/spark/pull/32401#pullrequestreview-705917468",
    "prSource" : "GitHub",
    "comments" : [
      {
        "id" : "99a0df6a-c6e2-4f70-a982-4faf31b60d56",
        "parentId" : null,
        "authorId" : "d35df420-57a9-43e8-b8d5-cad0f4002681",
        "body" : "nit: short circuit common case of `0 == partitionChecksums.length` with returning empty long array ?",
        "createdAt" : "2021-07-12T07:12:47Z",
        "updatedAt" : "2021-07-12T07:38:19Z",
        "lastEditedBy" : "d35df420-57a9-43e8-b8d5-cad0f4002681",
        "tags" : [
        ]
      },
      {
        "id" : "c30a9e1c-95bd-47b4-bc31-dcb80d3c65fc",
        "parentId" : "99a0df6a-c6e2-4f70-a982-4faf31b60d56",
        "authorId" : "171fe41b-96df-4362-a600-2d1f030de577",
        "body" : "it already returns the empty long array when `partitionChecksums` is empty? (it won't go through the for loop when `partitionChecksums` is empty.)\r\n\r\n",
        "createdAt" : "2021-07-12T15:21:25Z",
        "updatedAt" : "2021-07-12T15:21:25Z",
        "lastEditedBy" : "171fe41b-96df-4362-a600-2d1f030de577",
        "tags" : [
        ]
      },
      {
        "id" : "2772538f-cfad-4746-956a-c277d26dd769",
        "parentId" : "99a0df6a-c6e2-4f70-a982-4faf31b60d56",
        "authorId" : "d35df420-57a9-43e8-b8d5-cad0f4002681",
        "body" : "I was looking to avoid the allocs/looping ... nit micro optimization which is not worth it (I saw this in context of the other nits related to empty array :) ).",
        "createdAt" : "2021-07-14T06:57:42Z",
        "updatedAt" : "2021-07-14T06:58:35Z",
        "lastEditedBy" : "d35df420-57a9-43e8-b8d5-cad0f4002681",
        "tags" : [
        ]
      }
    ],
    "commit" : "4bdde58a3791691f275968b117eeff260ef3016f",
    "line" : 77,
    "diffHunk" : "@@ -1,1 +75,79 @@  }\n\n  public static long[] getChecksumValues(Checksum[] partitionChecksums) {\n    int numPartitions = partitionChecksums.length;\n    long[] checksumValues = new long[numPartitions];"
  },
  {
    "id" : "f05faccd-9af4-444d-83c2-1bbf4b512406",
    "prId" : 32401,
    "prUrl" : "https://github.com/apache/spark/pull/32401#pullrequestreview-704722509",
    "prSource" : "GitHub",
    "comments" : [
      {
        "id" : "c2bd7548-6740-4487-bb90-8d459dda5d16",
        "parentId" : null,
        "authorId" : "9953a478-bdd8-4f15-be59-f6f654ff85ae",
        "body" : "Nit: documentation is missing",
        "createdAt" : "2021-07-12T16:12:53Z",
        "updatedAt" : "2021-07-12T20:47:39Z",
        "lastEditedBy" : "9953a478-bdd8-4f15-be59-f6f654ff85ae",
        "tags" : [
        ]
      },
      {
        "id" : "03959a25-de7d-4547-8dae-adf68664f2f6",
        "parentId" : "c2bd7548-6740-4487-bb90-8d459dda5d16",
        "authorId" : "171fe41b-96df-4362-a600-2d1f030de577",
        "body" : "Added the doc. And marked it as private.",
        "createdAt" : "2021-07-13T03:58:27Z",
        "updatedAt" : "2021-07-13T03:58:27Z",
        "lastEditedBy" : "171fe41b-96df-4362-a600-2d1f030de577",
        "tags" : [
        ]
      }
    ],
    "commit" : "4bdde58a3791691f275968b117eeff260ef3016f",
    "line" : 34,
    "diffHunk" : "@@ -1,1 +32,36 @@ */\n@Private\npublic class ShuffleChecksumHelper {\n\n  /** Used when the checksum is disabled for shuffle. */"
  },
  {
    "id" : "0f41f577-82c6-4ec6-aa66-cab9a4b4aaf4",
    "prId" : 32401,
    "prUrl" : "https://github.com/apache/spark/pull/32401#pullrequestreview-705889316",
    "prSource" : "GitHub",
    "comments" : [
      {
        "id" : "3edd3b52-d8d9-4ac6-85ea-f5e1244678f8",
        "parentId" : null,
        "authorId" : "0c28e5da-df9b-4076-bb67-3b6878f1f4ce",
        "body" : "No license header.",
        "createdAt" : "2021-07-14T03:12:45Z",
        "updatedAt" : "2021-07-14T03:12:45Z",
        "lastEditedBy" : "0c28e5da-df9b-4076-bb67-3b6878f1f4ce",
        "tags" : [
        ]
      },
      {
        "id" : "dedc669d-b3ff-41b3-a5ec-73e57ef212f9",
        "parentId" : "3edd3b52-d8d9-4ac6-85ea-f5e1244678f8",
        "authorId" : "171fe41b-96df-4362-a600-2d1f030de577",
        "body" : "oh yeah, this's definately a mistake. Though, it doesn't seem to be related to `RAT` failure.",
        "createdAt" : "2021-07-14T04:49:33Z",
        "updatedAt" : "2021-07-14T04:49:33Z",
        "lastEditedBy" : "171fe41b-96df-4362-a600-2d1f030de577",
        "tags" : [
        ]
      },
      {
        "id" : "21658bea-8fb9-4cd0-964f-0c34ae5ab536",
        "parentId" : "3edd3b52-d8d9-4ac6-85ea-f5e1244678f8",
        "authorId" : "0c28e5da-df9b-4076-bb67-3b6878f1f4ce",
        "body" : "RAT is a license checker.\r\n\r\n> https://amplab.cs.berkeley.edu/jenkins/job/SparkPullRequestBuilder/140992/console\r\n\r\n```\r\n========================================================================\r\nRunning Apache RAT checks\r\n========================================================================\r\nAttempting to fetch rat\r\nCould not find Apache license headers in the following files:\r\n !????? /home/jenkins/workspace/SparkPullRequestBuilder/core/src/main/java/org/apache/spark/shuffle/checksum/ShuffleChecksumHelper.java\r\n[error] running /home/jenkins/workspace/SparkPullRequestBuilder/dev/check-license ; received return code 1\r\n```",
        "createdAt" : "2021-07-14T04:58:08Z",
        "updatedAt" : "2021-07-14T04:58:08Z",
        "lastEditedBy" : "0c28e5da-df9b-4076-bb67-3b6878f1f4ce",
        "tags" : [
        ]
      },
      {
        "id" : "4c7dcd6c-5867-43ff-bb01-eabe2aff8890",
        "parentId" : "3edd3b52-d8d9-4ac6-85ea-f5e1244678f8",
        "authorId" : "171fe41b-96df-4362-a600-2d1f030de577",
        "body" : "Oh I see. I was caught by the `FileNotFoundException` previously.",
        "createdAt" : "2021-07-14T06:14:03Z",
        "updatedAt" : "2021-07-14T06:14:03Z",
        "lastEditedBy" : "171fe41b-96df-4362-a600-2d1f030de577",
        "tags" : [
        ]
      }
    ],
    "commit" : "4bdde58a3791691f275968b117eeff260ef3016f",
    "line" : 18,
    "diffHunk" : "@@ -1,1 +16,20 @@ */\n\npackage org.apache.spark.shuffle.checksum;\n\nimport java.util.zip.Adler32;"
  }
]