[
  {
    "id" : "1595cdcd-0b91-4b4c-bc94-86622cd3cc75",
    "prId" : 29354,
    "prUrl" : "https://github.com/apache/spark/pull/29354#pullrequestreview-462011406",
    "prSource" : "GitHub",
    "comments" : [
      {
        "id" : "173ffc08-7733-48ca-b141-134af6925e51",
        "parentId" : null,
        "authorId" : "6e35521d-0def-4310-bc41-de4685fba931",
        "body" : "This method was needed to support \"expanding\" UnsafeArrayData object so that an intermediate expandable array is not needed.",
        "createdAt" : "2020-08-05T20:46:58Z",
        "updatedAt" : "2020-08-06T19:18:51Z",
        "lastEditedBy" : "6e35521d-0def-4310-bc41-de4685fba931",
        "tags" : [
        ]
      }
    ],
    "commit" : "054d60229e7a6eb31da1be3f23ac1f2b59a95261",
    "line" : 13,
    "diffHunk" : "@@ -1,1 +366,370 @@      toArray.baseObject, toArray.elementOffset,\n      Math.min(this.sizeInBytes - this.elementOffset, toArray.sizeInBytes - toArray.elementOffset));\n  }\n\n  @Override"
  }
]