[
  {
    "id" : "a35a2192-07fe-4ab8-91ce-ac5f3f208445",
    "prId" : 28995,
    "prUrl" : "https://github.com/apache/spark/pull/28995#pullrequestreview-442635538",
    "prSource" : "GitHub",
    "comments" : [
      {
        "id" : "a3546645-e838-48e9-9a18-d5799e274427",
        "parentId" : null,
        "authorId" : "044062b3-9d96-4ec3-a1e2-3a2f595bbc02",
        "body" : "Ah, I see. Nice catch!",
        "createdAt" : "2020-07-04T23:09:48Z",
        "updatedAt" : "2020-07-04T23:09:48Z",
        "lastEditedBy" : "044062b3-9d96-4ec3-a1e2-3a2f595bbc02",
        "tags" : [
        ]
      }
    ],
    "commit" : "10b1928b08a0200dea50223aa9ef2012f1c641b8",
    "line" : 5,
    "diffHunk" : "@@ -1,1 +140,144 @@              url: sql-ref-syntax-ddl-repair-table.html\n            - text: USE DATABASE\n              url: sql-ref-syntax-ddl-usedb.html\n        - text: Data Manipulation Statements\n          url: sql-ref-syntax-dml.html"
  },
  {
    "id" : "c15f1496-6577-4074-9ad6-f6e62f0207ea",
    "prId" : 28451,
    "prUrl" : "https://github.com/apache/spark/pull/28451#pullrequestreview-405448179",
    "prSource" : "GitHub",
    "comments" : [
      {
        "id" : "28afda49-891f-4deb-b72b-075f76009f17",
        "parentId" : null,
        "authorId" : "044062b3-9d96-4ec3-a1e2-3a2f595bbc02",
        "body" : "Why do we need the changes in this file?",
        "createdAt" : "2020-05-04T23:39:05Z",
        "updatedAt" : "2020-05-05T16:09:41Z",
        "lastEditedBy" : "044062b3-9d96-4ec3-a1e2-3a2f595bbc02",
        "tags" : [
        ]
      },
      {
        "id" : "210e337e-a143-44e9-ada0-3df908c7d057",
        "parentId" : "28afda49-891f-4deb-b72b-075f76009f17",
        "authorId" : "99765afe-8dbe-4d5f-9ad3-d5bc40f0462b",
        "body" : "I didn't change the order of the first 8 clauses. I think these should be grouped together. But I changed the rest to make them alphabetical order.\r\n<img width=\"201\" alt=\"Screen Shot 2020-05-04 at 6 22 05 PM\" src=\"https://user-images.githubusercontent.com/13592258/81027881-33663000-8e34-11ea-9305-3d62a1769362.png\">\r\n",
        "createdAt" : "2020-05-05T01:24:57Z",
        "updatedAt" : "2020-05-05T16:09:41Z",
        "lastEditedBy" : "99765afe-8dbe-4d5f-9ad3-d5bc40f0462b",
        "tags" : [
        ]
      }
    ],
    "commit" : "bd82fdd6d132020a72d8f1ed3f4327e3b334555b",
    "line" : 14,
    "diffHunk" : "@@ -1,1 +167,171 @@                - text: LIKE Predicate\n                  url: sql-ref-syntax-qry-select-like.html\n                - text: Set Operators\n                  url: sql-ref-syntax-qry-select-setops.html\n                - text: TABLESAMPLE"
  },
  {
    "id" : "2e64b6fc-9392-4dff-8235-8e3f7519517c",
    "prId" : 28264,
    "prUrl" : "https://github.com/apache/spark/pull/28264#pullrequestreview-396199986",
    "prSource" : "GitHub",
    "comments" : [
      {
        "id" : "826c8d83-99e9-4853-9891-ab424066b08a",
        "parentId" : null,
        "authorId" : "044062b3-9d96-4ec3-a1e2-3a2f595bbc02",
        "body" : "The null semantics is also a sub category of the data types section?",
        "createdAt" : "2020-04-20T01:00:00Z",
        "updatedAt" : "2020-04-24T17:03:49Z",
        "lastEditedBy" : "044062b3-9d96-4ec3-a1e2-3a2f595bbc02",
        "tags" : [
        ]
      },
      {
        "id" : "5ae6bd4d-e8ad-4eaf-b227-b9e77c73769b",
        "parentId" : "826c8d83-99e9-4853-9891-ab424066b08a",
        "authorId" : "99765afe-8dbe-4d5f-9ad3-d5bc40f0462b",
        "body" : "I scanned through the null semantics file, seems to me it's not a sub category of the data types section.",
        "createdAt" : "2020-04-20T07:24:19Z",
        "updatedAt" : "2020-04-24T17:03:49Z",
        "lastEditedBy" : "99765afe-8dbe-4d5f-9ad3-d5bc40f0462b",
        "tags" : [
        ]
      }
    ],
    "commit" : "0499c08eb4597c3591858e9c2f5ff5cd5ff680e3",
    "line" : 3,
    "diffHunk" : "@@ -1,1 +80,84 @@      url: sql-ref-datatypes.html\n    - text: Null Semantics\n      url: sql-ref-null-semantics.html\n    - text: ANSI Compliance\n      url: sql-ref-ansi-compliance.html"
  },
  {
    "id" : "22161c6b-330c-4e91-91a1-ad6b7726f68a",
    "prId" : 28224,
    "prUrl" : "https://github.com/apache/spark/pull/28224#pullrequestreview-395829177",
    "prSource" : "GitHub",
    "comments" : [
      {
        "id" : "3596292a-354e-4ee9-9ecc-914ad201861d",
        "parentId" : null,
        "authorId" : "5e07d5ab-b4b3-41e4-beca-fefd635980c6",
        "body" : "Okay .. now I understood why you included the generated file and why it's tricky. We should exclude `sql-ref-functions-builtin.html` conditionally but it's difficult because the generated file is md file.\r\n\r\nWe can't easily directly generate `sql-ref-functions-builtin.html` either because Jekyll adds some links and htmls when it converts md to html.",
        "createdAt" : "2020-04-17T15:12:09Z",
        "updatedAt" : "2020-04-21T00:28:49Z",
        "lastEditedBy" : "5e07d5ab-b4b3-41e4-beca-fefd635980c6",
        "tags" : [
        ]
      },
      {
        "id" : "1db536e2-e8b7-4070-bc96-6e68718cce06",
        "parentId" : "3596292a-354e-4ee9-9ecc-914ad201861d",
        "authorId" : "5e07d5ab-b4b3-41e4-beca-fefd635980c6",
        "body" : "Maybe we should keep `sql-ref-functions-builtin.md` as:\r\n\r\n```\r\n{% for static_file in site.static_files %}\r\n    {% if static_file.name == 'agg_funcs.html' %}\r\n### Aggregate Functions\r\n        {% include_relative agg_funcs.html %}\r\n#### Examples\r\n        {% include_relative agg_funcs_examples.html %}\r\n        {% break %}\r\n    {% endif %}\r\n{% endfor %}\r\n\r\n{% for static_file in site.static_files %}\r\n    {% if static_file.name == 'window_funcs.html' %}\r\n### Windows Functions\r\n        {% include_relative window_funcs.html %}\r\n#### Examples\r\n        {% include_relative window_funcs_examples.html %}\r\n        {% break %}\r\n    {% endif %}\r\n{% endfor %}\r\n\r\n...\r\n```",
        "createdAt" : "2020-04-17T15:16:03Z",
        "updatedAt" : "2020-04-21T00:28:49Z",
        "lastEditedBy" : "5e07d5ab-b4b3-41e4-beca-fefd635980c6",
        "tags" : [
        ]
      },
      {
        "id" : "d2163981-53b7-46b6-9f33-575cdfa0ad66",
        "parentId" : "3596292a-354e-4ee9-9ecc-914ad201861d",
        "authorId" : "5e07d5ab-b4b3-41e4-beca-fefd635980c6",
        "body" : "`mkdocs.markdown` should be able to produce a pretty HTML from MD for examples as well. Let me take another look tomorrow night or a day after tomorrow .. and push some more changes ...",
        "createdAt" : "2020-04-17T15:17:53Z",
        "updatedAt" : "2020-04-21T00:28:49Z",
        "lastEditedBy" : "5e07d5ab-b4b3-41e4-beca-fefd635980c6",
        "tags" : [
        ]
      },
      {
        "id" : "aee60cb3-e6b6-4a41-a75f-e47f551d3f7b",
        "parentId" : "3596292a-354e-4ee9-9ecc-914ad201861d",
        "authorId" : "044062b3-9d96-4ec3-a1e2-3a2f595bbc02",
        "body" : "Ah, I see and I didn't have that idea. ok, I'll wait for your more updates. Thanks for the work, anyway.",
        "createdAt" : "2020-04-17T23:51:13Z",
        "updatedAt" : "2020-04-21T00:28:49Z",
        "lastEditedBy" : "044062b3-9d96-4ec3-a1e2-3a2f595bbc02",
        "tags" : [
        ]
      }
    ],
    "commit" : "f302c91fc270fb4a7607381c3ca1af7ccbecd7c1",
    "line" : 5,
    "diffHunk" : "@@ -1,1 +244,248 @@      subitems:\n      - text: Built-in Functions\n        url: sql-ref-functions-builtin.html\n      - text: Scalar UDFs (User-Defined Functions)\n        url: sql-ref-functions-udf-scalar.html"
  },
  {
    "id" : "ecd996cd-1c9b-4142-8018-41c5cf48e1c0",
    "prId" : 27371,
    "prUrl" : "https://github.com/apache/spark/pull/27371#pullrequestreview-349153434",
    "prSource" : "GitHub",
    "comments" : [
      {
        "id" : "517cb8d6-c03c-4076-81e3-4c5ceb5298dc",
        "parentId" : null,
        "authorId" : "044062b3-9d96-4ec3-a1e2-3a2f595bbc02",
        "body" : "The order of these clauses depends on something? Can we reorder them along with the main menu? https://github.com/apache/spark/blob/master/docs/sql-ref-syntax-qry-select.md",
        "createdAt" : "2020-01-28T03:35:47Z",
        "updatedAt" : "2020-01-28T06:25:16Z",
        "lastEditedBy" : "044062b3-9d96-4ec3-a1e2-3a2f595bbc02",
        "tags" : [
        ]
      },
      {
        "id" : "e4fe0993-1c47-4f25-96f2-1d81c4f2103b",
        "parentId" : "517cb8d6-c03c-4076-81e3-4c5ceb5298dc",
        "authorId" : "a2fcc15e-a51a-42f0-87a6-137048a28e30",
        "body" : "@maropu Did you want me to re-order menu in the left hand side panel as per the \"related clauses\" in https://github.com/apache/spark/blob/master/docs/sql-ref-syntax-qry-select.md ? i.e \r\n```\r\n- [WHERE Clause](sql-ref-syntax-qry-select-where.html)\r\n- [GROUP BY Clause](sql-ref-syntax-qry-select-groupby.html)\r\n- [HAVING Clause](sql-ref-syntax-qry-select-having.html)\r\n- [ORDER BY Clause](sql-ref-syntax-qry-select-orderby.html)\r\n- [SORT BY Clause](sql-ref-syntax-qry-select-sortby.html)\r\n- [CLUSTER BY Clause](sql-ref-syntax-qry-select-clusterby.html)\r\n- [DISTRIBUTE BY Clause](sql-ref-syntax-qry-select-distribute-by.html)\r\n- [LIMIT Clause](sql-ref-syntax-qry-select-limit.html)\r\n```",
        "createdAt" : "2020-01-28T05:24:32Z",
        "updatedAt" : "2020-01-28T06:25:16Z",
        "lastEditedBy" : "a2fcc15e-a51a-42f0-87a6-137048a28e30",
        "tags" : [
        ]
      },
      {
        "id" : "20e9f295-7176-442a-a9ab-be4608639171",
        "parentId" : "517cb8d6-c03c-4076-81e3-4c5ceb5298dc",
        "authorId" : "044062b3-9d96-4ec3-a1e2-3a2f595bbc02",
        "body" : "Yea, can we?",
        "createdAt" : "2020-01-28T05:42:29Z",
        "updatedAt" : "2020-01-28T06:25:16Z",
        "lastEditedBy" : "044062b3-9d96-4ec3-a1e2-3a2f595bbc02",
        "tags" : [
        ]
      },
      {
        "id" : "375cda2f-08bd-485b-a316-5f37e93538da",
        "parentId" : "517cb8d6-c03c-4076-81e3-4c5ceb5298dc",
        "authorId" : "a2fcc15e-a51a-42f0-87a6-137048a28e30",
        "body" : "@maropu Sure... will do.",
        "createdAt" : "2020-01-28T05:46:08Z",
        "updatedAt" : "2020-01-28T06:25:16Z",
        "lastEditedBy" : "a2fcc15e-a51a-42f0-87a6-137048a28e30",
        "tags" : [
        ]
      },
      {
        "id" : "41d8f9a7-ed64-4815-b6bd-f5bf0668f664",
        "parentId" : "517cb8d6-c03c-4076-81e3-4c5ceb5298dc",
        "authorId" : "a2fcc15e-a51a-42f0-87a6-137048a28e30",
        "body" : "@maropu I have reconciled the link order. Also i have added a very brief description in the entry page which looks like this : \r\n<img width=\"972\" alt=\"Screen Shot 2020-01-27 at 10 35 17 PM\" src=\"https://user-images.githubusercontent.com/14225158/73240922-527a6500-4155-11ea-94e3-dc84bc7e642b.png\">\r\n\r\nPlease see if this looks okay to you or if we want to re-word or add anything ?\r\n\r\ncc @huaxingao @srowen ",
        "createdAt" : "2020-01-28T06:36:37Z",
        "updatedAt" : "2020-01-28T06:36:38Z",
        "lastEditedBy" : "a2fcc15e-a51a-42f0-87a6-137048a28e30",
        "tags" : [
        ]
      }
    ],
    "commit" : "b4b6612c5aa720a121295f69605bd0873068af30",
    "line" : 10,
    "diffHunk" : "@@ -1,1 +124,128 @@              url: sql-ref-syntax-qry-select.html \n              subitems:\n                - text: WHERE Clause \n                  url: sql-ref-syntax-qry-select-where.html\n                - text: GROUP BY Clause "
  }
]