[
  {
    "id" : "4c3c5e19-9ffa-4f2c-8209-3078f0befdfd",
    "prId" : 26498,
    "prUrl" : "https://github.com/apache/spark/pull/26498#pullrequestreview-316242310",
    "prSource" : "GitHub",
    "comments" : [
      {
        "id" : "dc430cd8-0054-4187-adaa-92accac75f9e",
        "parentId" : null,
        "authorId" : "707cf6e1-750c-4aea-8774-f79c13fb7add",
        "body" : "This one isn't important enough to bother with, I think. The data is small",
        "createdAt" : "2019-11-13T13:30:22Z",
        "updatedAt" : "2019-11-13T13:30:26Z",
        "lastEditedBy" : "707cf6e1-750c-4aea-8774-f79c13fb7add",
        "tags" : [
        ]
      }
    ],
    "commit" : "800cd25da2549c8f66807e4650d5bfd34b82e3c4",
    "line" : 4,
    "diffHunk" : "@@ -1,1 +199,203 @@      .map(_.split(\",\"))\n      .map(attributes => Person(attributes(0), attributes(1).trim.toInt))\n      .cache()\n      .toDF()\n    // Register the DataFrame as a temporary view"
  }
]