[
  {
    "id" : "f09c14e4-43c3-4b18-9904-f4b8421266bf",
    "prId" : 25947,
    "prUrl" : "https://github.com/apache/spark/pull/25947#pullrequestreview-294607364",
    "prSource" : "GitHub",
    "comments" : [
      {
        "id" : "c0dbbc1d-3122-45f6-a7ab-230dbf75e8e2",
        "parentId" : null,
        "authorId" : "5e28de51-305c-4276-b3a0-78bcc74eb6f2",
        "body" : "These are newly added, right? So which one is more correct, since(1.4.0) or since(3.0.0)?",
        "createdAt" : "2019-09-27T21:00:36Z",
        "updatedAt" : "2019-10-03T22:24:41Z",
        "lastEditedBy" : "5e28de51-305c-4276-b3a0-78bcc74eb6f2",
        "tags" : [
        ]
      },
      {
        "id" : "ec7a2251-88b1-4e38-83e2-488a8d32e33f",
        "parentId" : "c0dbbc1d-3122-45f6-a7ab-230dbf75e8e2",
        "authorId" : "99765afe-8dbe-4d5f-9ad3-d5bc40f0462b",
        "body" : "Should be since(3.0.0). Thanks for catching that problem. ",
        "createdAt" : "2019-09-28T00:05:05Z",
        "updatedAt" : "2019-10-03T22:24:41Z",
        "lastEditedBy" : "99765afe-8dbe-4d5f-9ad3-d5bc40f0462b",
        "tags" : [
        ]
      }
    ],
    "commit" : "1d1f041ba9fc048d5657bd8caf0adbd61e5f2066",
    "line" : 388,
    "diffHunk" : "@@ -1,1 +412,416 @@\n    @since(\"3.0.0\")\n    def setUserCol(self, value):\n        \"\"\"\n        Sets the value of :py:attr:`userCol`."
  }
]