[
  {
    "id" : "4d3d7837-96c5-44a3-a1e0-f47da160ce73",
    "prId" : 26496,
    "prUrl" : "https://github.com/apache/spark/pull/26496#pullrequestreview-358670030",
    "prSource" : "GitHub",
    "comments" : [
      {
        "id" : "a0397ed4-aee0-495f-b285-363c10ab773e",
        "parentId" : null,
        "authorId" : "2d6b46ba-4100-4c4d-9341-fff5e39647ec",
        "body" : "nit: Could we mention that this must be set for all processes? For example, `set the environment variable `PYSPARK_ROW_FIELD_SORTING_ENABLED` to \"true\" for **executors and driver**. This env must be consistent on all executors and driver. Any inconsistency may cause failures or incorrect answers `",
        "createdAt" : "2020-02-14T00:28:27Z",
        "updatedAt" : "2020-02-14T00:28:27Z",
        "lastEditedBy" : "2d6b46ba-4100-4c4d-9341-fff5e39647ec",
        "tags" : [
        ]
      },
      {
        "id" : "f76a30b8-0903-4a9c-b9f6-691a259de127",
        "parentId" : "a0397ed4-aee0-495f-b285-363c10ab773e",
        "authorId" : "5e07d5ab-b4b3-41e4-beca-fefd635980c6",
        "body" : "+1. Let me fix it.",
        "createdAt" : "2020-02-14T01:51:37Z",
        "updatedAt" : "2020-02-14T01:51:37Z",
        "lastEditedBy" : "5e07d5ab-b4b3-41e4-beca-fefd635980c6",
        "tags" : [
        ]
      }
    ],
    "commit" : "14e691d3fba4dd416d88f84d0cb5e7489cd69aa3",
    "line" : 4,
    "diffHunk" : "@@ -1,1 +88,92 @@    For example, `map_col.getItem(col('id'))` should be replaced with `map_col[col('id')]`.\n\n  - As of Spark 3.0 `Row` field names are no longer sorted alphabetically when constructing with named arguments for Python versions 3.6 and above, and the order of fields will match that as entered. To enable sorted fields by default, as in Spark 2.4, set the environment variable `PYSPARK_ROW_FIELD_SORTING_ENABLED` to \"true\". For Python versions less than 3.6, the field names will be sorted alphabetically as the only option.\n\n## Upgrading from PySpark 2.3 to 2.4"
  },
  {
    "id" : "44cace90-a82d-4001-833c-7368ba7404a5",
    "prId" : 25757,
    "prUrl" : "https://github.com/apache/spark/pull/25757#pullrequestreview-288170210",
    "prSource" : "GitHub",
    "comments" : [
      {
        "id" : "1fdcbd65-7556-43ef-8710-1c957a166256",
        "parentId" : null,
        "authorId" : "5e28de51-305c-4276-b3a0-78bcc74eb6f2",
        "body" : "\"spark.sql.execution.arrow.enabled=true\" => ``` `spark.sql.execution.arrow.enabled`=true ``` or ``` `spark.sql.execution.arrow.enabled` set to `True` ```?",
        "createdAt" : "2019-09-13T18:06:29Z",
        "updatedAt" : "2019-09-13T18:08:01Z",
        "lastEditedBy" : "5e28de51-305c-4276-b3a0-78bcc74eb6f2",
        "tags" : [
        ]
      }
    ],
    "commit" : "7a8d63922d6654c5ab515967a58d9070a64d4407",
    "line" : 33,
    "diffHunk" : "@@ -1,1 +31,35 @@  - Since Spark 3.0, PySpark requires a Pandas version of 0.23.2 or higher to use Pandas related functionality, such as `toPandas`, `createDataFrame` from Pandas DataFrame, etc.\n\n  - Since Spark 3.0, PySpark requires a PyArrow version of 0.12.1 or higher to use PyArrow related functionality, such as `pandas_udf`, `toPandas` and `createDataFrame` with \"spark.sql.execution.arrow.enabled=true\", etc.\n\n  - In PySpark, when creating a `SparkSession` with `SparkSession.builder.getOrCreate()`, if there is an existing `SparkContext`, the builder was trying to update the `SparkConf` of the existing `SparkContext` with configurations specified to the builder, but the `SparkContext` is shared by all `SparkSession`s, so we should not update them. Since 3.0, the builder comes to not update the configurations. This is the same behavior as Java/Scala API in 2.3 and above. If you want to update them, you need to update them prior to creating a `SparkSession`."
  },
  {
    "id" : "616d464f-59ab-4efa-ae40-87235a04c58b",
    "prId" : 25757,
    "prUrl" : "https://github.com/apache/spark/pull/25757#pullrequestreview-288174223",
    "prSource" : "GitHub",
    "comments" : [
      {
        "id" : "ae10febd-cfd5-4513-a791-c4261221e0f3",
        "parentId" : null,
        "authorId" : "5e28de51-305c-4276-b3a0-78bcc74eb6f2",
        "body" : "``` `DataFrame.withColumn` ```",
        "createdAt" : "2019-09-13T18:14:27Z",
        "updatedAt" : "2019-09-13T18:14:42Z",
        "lastEditedBy" : "5e28de51-305c-4276-b3a0-78bcc74eb6f2",
        "tags" : [
        ]
      }
    ],
    "commit" : "7a8d63922d6654c5ab515967a58d9070a64d4407",
    "line" : 111,
    "diffHunk" : "@@ -1,1 +109,113 @@   your column name contains any dots you must now escape them using backticks (e.g., ``table.`column.with.dots`.nested``).\n\n - DataFrame.withColumn method in PySpark supports adding a new column or replacing existing columns of the same name.\n\n"
  }
]