[
  {
    "id" : "4b205341-edf9-4952-a4fd-d0a9b5facc36",
    "prId" : 31085,
    "prUrl" : "https://github.com/apache/spark/pull/31085#pullrequestreview-563912502",
    "prSource" : "GitHub",
    "comments" : [
      {
        "id" : "8c5c3879-c330-458f-b753-82819513419e",
        "parentId" : null,
        "authorId" : "9ae00886-75a7-4f39-aed7-d47b26b67afb",
        "body" : "nit: also need to update above: \"three options\" -> \"four options\".",
        "createdAt" : "2021-01-07T23:44:05Z",
        "updatedAt" : "2021-01-08T00:00:17Z",
        "lastEditedBy" : "9ae00886-75a7-4f39-aed7-d47b26b67afb",
        "tags" : [
        ]
      },
      {
        "id" : "a7578f7f-a8f1-43a2-a7ff-0549093e2684",
        "parentId" : "8c5c3879-c330-458f-b753-82819513419e",
        "authorId" : "7694af3d-5af2-4788-8413-c0558915c452",
        "body" : "Thanks!",
        "createdAt" : "2021-01-07T23:55:17Z",
        "updatedAt" : "2021-01-08T00:00:17Z",
        "lastEditedBy" : "7694af3d-5af2-4788-8413-c0558915c452",
        "tags" : [
        ]
      }
    ],
    "commit" : "6f9241e47ed6060d12be4e609eaf839003d0221a",
    "line" : 13,
    "diffHunk" : "@@ -1,1 +149,153 @@        Use Hive jars of specified version downloaded from Maven repositories. This configuration\n        is not generally recommended for production deployments.\n        <li><code>path</code></li>\n        Use Hive jars configured by <code>spark.sql.hive.metastore.jars.path</code>\n        in comma separated format. Support both local or remote paths."
  },
  {
    "id" : "40506649-83aa-4b6a-ba90-643f8c133728",
    "prId" : 31085,
    "prUrl" : "https://github.com/apache/spark/pull/31085#pullrequestreview-563945418",
    "prSource" : "GitHub",
    "comments" : [
      {
        "id" : "7b924bae-59a7-4f92-9c62-47b06fde8d54",
        "parentId" : null,
        "authorId" : "9ae00886-75a7-4f39-aed7-d47b26b67afb",
        "body" : "I remember there were discussion about using S3 as path in the original PR but it is not supported yet, is that correct? there could be edge cases where ppl set `fs.defaultFS` to a S3 path.\r\n\r\nAlso is viewfs supported as well? it's common ppl set that for `fs.defaultFS` too.",
        "createdAt" : "2021-01-07T23:47:27Z",
        "updatedAt" : "2021-01-08T00:00:17Z",
        "lastEditedBy" : "9ae00886-75a7-4f39-aed7-d47b26b67afb",
        "tags" : [
        ]
      },
      {
        "id" : "d2005d6d-762c-4a7b-ae9b-4e0017cf1c4c",
        "parentId" : "7b924bae-59a7-4f92-9c62-47b06fde8d54",
        "authorId" : "ddb80038-2da6-4937-8c45-4d52fbe0300f",
        "body" : "+1 on this, I just glanced at #29881 and it seems any Hadoop FileSystem should be allowed here rather than just `file`/`hdfs`?",
        "createdAt" : "2021-01-07T23:54:09Z",
        "updatedAt" : "2021-01-08T00:00:17Z",
        "lastEditedBy" : "ddb80038-2da6-4937-8c45-4d52fbe0300f",
        "tags" : [
        ]
      },
      {
        "id" : "6a1ce477-611b-406e-aa5e-b7e41fe12e43",
        "parentId" : "7b924bae-59a7-4f92-9c62-47b06fde8d54",
        "authorId" : "7694af3d-5af2-4788-8413-c0558915c452",
        "body" : "Thanks, @sunchao and @xkrogen .\r\n\r\n1. For `S3`, in fact, I'm the one who asked about `S3` clarification. I didn't see any comment about not supporting it. I guess it's supported but not described because it requires `hadoop-cloud` module.\r\n2. For `views`, I believe so.\r\n\r\nBTW, this document came from the existing document of that `conf` description. For now, let's keep this identical with that. We can update both of them together later.",
        "createdAt" : "2021-01-07T23:58:41Z",
        "updatedAt" : "2021-01-08T00:00:17Z",
        "lastEditedBy" : "7694af3d-5af2-4788-8413-c0558915c452",
        "tags" : [
        ]
      },
      {
        "id" : "6e9cef5a-9d01-4ecb-bdc6-c692cba8a175",
        "parentId" : "7b924bae-59a7-4f92-9c62-47b06fde8d54",
        "authorId" : "9ae00886-75a7-4f39-aed7-d47b26b67afb",
        "body" : "Yes, sounds good to me. \r\n\r\nI remember @AngersZhuuuu mentioned some stackoverflow exception when using S3 as path but I don't know whether that is resolved afterwards.\r\n\r\n",
        "createdAt" : "2021-01-08T00:01:32Z",
        "updatedAt" : "2021-01-08T00:01:32Z",
        "lastEditedBy" : "9ae00886-75a7-4f39-aed7-d47b26b67afb",
        "tags" : [
        ]
      },
      {
        "id" : "41b67a74-d98a-4ab0-978d-7e0830842419",
        "parentId" : "7b924bae-59a7-4f92-9c62-47b06fde8d54",
        "authorId" : "594db420-88ec-4875-8cd3-0d8b0bec131c",
        "body" : "> Yes, sounds good to me.\r\n> \r\n> I remember @AngersZhuuuu mentioned some stackoverflow exception when using S3 as path but I don't know whether that is resolved afterwards.\r\n\r\nYea, a stackoverflow seems caused by classloader. Not resolved yet since it rely on thirdparty jars.",
        "createdAt" : "2021-01-08T01:30:16Z",
        "updatedAt" : "2021-01-08T01:30:16Z",
        "lastEditedBy" : "594db420-88ec-4875-8cd3-0d8b0bec131c",
        "tags" : [
        ]
      }
    ],
    "commit" : "6f9241e47ed6060d12be4e609eaf839003d0221a",
    "line" : 34,
    "diffHunk" : "@@ -1,1 +171,175 @@        <li><code>file://path/to/jar/foo.jar</code></li>\n        <li><code>hdfs://nameservice/path/to/jar/foo.jar</code></li>\n        <li><code>/path/to/jar/</code>(path without URI scheme follow conf <code>fs.defaultFS</code>'s URI schema)</li>\n        <li><code>[http/https/ftp]://path/to/jar/foo.jar</code></li>\n      </ol>"
  }
]